jlserve/__init__.py
jlserve/cli.py
jlserve/cli_test.py
jlserve/decorator.py
jlserve/decorator_test.py
jlserve/exceptions.py
jlserve/integration_test.py
jlserve/requirements.py
jlserve/requirements_test.py
jlserve/server.py
jlserve/server_test.py
jlserve/validator.py
jlserve/validator_test.py
jlserve-0.1.0.dist-info/METADATA
jlserve-0.1.0.dist-info/WHEEL
jlserve-0.1.0.dist-info/entry_points.txt
jlserve-0.1.0.dist-info/licenses/LICENSE
jlserve-0.1.0.dist-info/RECORD
