Metadata-Version: 2.4
Name: jlserve
Version: 0.1.0
Summary: A simple framework for creating ML endpoints
Project-URL: Homepage, https://github.com/svishnu88/jlserve
Project-URL: Repository, https://github.com/svishnu88/jlserve
Project-URL: Issues, https://github.com/svishnu88/jlserve/issues
Author-email: Vishnu Subramanian <vishnu@jarvislabs.ai>
License: MIT
License-File: LICENSE
Keywords: endpoints,fastapi,inference,machine-learning,ml
Classifier: Development Status :: 3 - Alpha
Classifier: Intended Audience :: Developers
Classifier: License :: OSI Approved :: MIT License
Classifier: Programming Language :: Python :: 3
Classifier: Programming Language :: Python :: 3.10
Classifier: Programming Language :: Python :: 3.11
Classifier: Programming Language :: Python :: 3.12
Classifier: Topic :: Scientific/Engineering :: Artificial Intelligence
Classifier: Topic :: Software Development :: Libraries :: Python Modules
Requires-Python: >=3.10
Requires-Dist: fastapi>=0.115.0
Requires-Dist: pydantic>=2.0.0
Requires-Dist: typer>=0.15.0
Requires-Dist: uvicorn>=0.32.0
